mockmaster/__init__.py
mockmaster/cli.py
mockmaster/mockmaster.py
mockmaster/utils.py
mockmaster-0.0.2.dist-info/LICENSE
mockmaster-0.0.2.dist-info/METADATA
mockmaster-0.0.2.dist-info/WHEEL
mockmaster-0.0.2.dist-info/entry_points.txt
mockmaster-0.0.2.dist-info/top_level.txt
mockmaster-0.0.2.dist-info/RECORD
