Metadata-Version: 2.1
Name: mockmaster
Version: 0.0.2
Summary: A CLI tool to generate dummy data 
Author: Deepu Krishnareddy , Harish Mohan
Author-email: deepukreddy007@gmail.com , Harishmohan1598@gmail.com
License: MIT
Keywords: data dummy
Classifier: Development Status :: 2 - Pre-Alpha
Classifier: Topic :: Utilities
License-File: LICENSE
Requires-Dist: openai
Requires-Dist: pandas
Requires-Dist: jsonschema
Requires-Dist: python-dotenv
Requires-Dist: pyfiglet
Requires-Dist: tabulate
Requires-Dist: termcolor
